{
  "sourceHandle": "concept://dashboard_events_and_read_models",
  "targetHandle": "concept://coordination_and_plan_runtime",
  "kind": "depends_on",
  "confidence": 0.9,
  "evidence": [
    "Dashboard read models surface active tasks, blockers, and runtime coordination state rather than only static metadata."
  ],
  "scope": "repo",
  "provenance": {
    "origin": "manual_concept_relation",
    "kind": "manual_concept_relation",
    "taskId": "task:map-the-full-prism-architecture-into-durable-repo-concepts-and-concept-relations-for-future-agent-reasoning:85"
  }
}
