{
  "id": "coord-task:01kna8tv5khkd6ypdg9q6dfs87",
  "plan": "plan:01kna8sczaf3vhy8q6erq4fdvr",
  "kind": "Edit",
  "title": "Add shared coordination runtime descriptors for live runtime discovery and capability advertisement",
  "summary": null,
  "status": "Ready",
  "published_task_status": null,
  "assignee": null,
  "pending_handoff_to": null,
  "session": null,
  "lease_holder": null,
  "lease_started_at": null,
  "lease_refreshed_at": null,
  "lease_stale_at": null,
  "lease_expires_at": null,
  "worktree_id": null,
  "branch_ref": null,
  "anchors": [],
  "bindings": {
    "anchors": [],
    "concept_handles": [],
    "artifact_refs": [],
    "memory_refs": [],
    "outcome_refs": []
  },
  "depends_on": [
    "coord-task:01kna8tgf7s523e5edfv0gc0v9"
  ],
  "acceptance": [],
  "validation_refs": [],
  "is_abstract": false,
  "base_revision": {
    "graph_version": 152,
    "git_commit": null
  },
  "priority": null,
  "tags": [],
  "metadata": null,
  "git_execution": {
    "status": "not_started",
    "pendingTaskStatus": null,
    "sourceRef": null,
    "targetRef": null,
    "publishRef": null,
    "targetBranch": null,
    "lastPreflight": null,
    "lastPublish": null
  }
}
