{
  "plan": {
    "id": "plan:01knadcr3p15he31394q1bs5wv",
    "goal": "Finish the remaining shared coordination ref work by adding CAS retry/reconciliation, remote live-sync, target integration lifecycle/evidence, and shared-ref retention/compaction.",
    "title": "Complete shared coordination refs follow-through",
    "status": "Completed",
    "policy": {
      "default_claim_mode": "Advisory",
      "max_parallel_editors_per_anchor": 2,
      "require_review_for_completion": false,
      "require_validation_for_completion": false,
      "stale_after_graph_change": true,
      "review_required_above_risk_score": null,
      "lease_stale_after_seconds": 1800,
      "lease_expires_after_seconds": 7200,
      "lease_renewal_mode": "strict",
      "git_execution": {
        "startMode": "off",
        "completionMode": "off",
        "targetRef": null,
        "targetBranch": "main",
        "requireTaskBranch": false,
        "maxCommitsBehindTarget": 0,
        "maxFetchAgeSeconds": null,
        "integrationMode": "external"
      }
    },
    "scope": "Repo",
    "kind": "TaskExecution",
    "revision": 0,
    "scheduling": {
      "importance": 0,
      "urgency": 0,
      "manualBoost": 0,
      "dueAt": null
    },
    "tags": [],
    "created_from": null,
    "metadata": null,
    "authored_edges": [],
    "root_tasks": [
      "coord-task:01knadd8hh7hxr20jgcc46ywhe",
      "coord-task:01knaddam3fvr96xdqdxn2xdsj",
      "coord-task:01knaddcdxvdyh8akrc10b9npw",
      "coord-task:01knaddebyw5yp2vex9e8fgfm7"
    ]
  },
  "graph": {
    "id": "plan:01knadcr3p15he31394q1bs5wv",
    "scope": "Repo",
    "kind": "TaskExecution",
    "title": "Complete shared coordination refs follow-through",
    "goal": "Finish the remaining shared coordination ref work by adding CAS retry/reconciliation, remote live-sync, target integration lifecycle/evidence, and shared-ref retention/compaction.",
    "status": "Completed",
    "revision": 0,
    "root_nodes": [
      "coord-task:01knadd8hh7hxr20jgcc46ywhe",
      "coord-task:01knaddam3fvr96xdqdxn2xdsj",
      "coord-task:01knaddcdxvdyh8akrc10b9npw",
      "coord-task:01knaddebyw5yp2vex9e8fgfm7"
    ],
    "tags": [],
    "created_from": null,
    "metadata": null,
    "nodes": [
      {
        "id": "coord-task:01knadd8hh7hxr20jgcc46ywhe",
        "plan_id": "plan:01knadcr3p15he31394q1bs5wv",
        "kind": "Edit",
        "title": "Add CAS retry and retry-safe shared ref reconciliation",
        "summary": null,
        "status": "Completed",
        "bindings": {
          "anchors": [],
          "concept_handles": [],
          "artifact_refs": [],
          "memory_refs": [],
          "outcome_refs": []
        },
        "acceptance": [
          {
            "label": "Shared coordination writes refetch, re-evaluate, and retry on compare-and-swap push races.",
            "anchors": [],
            "required_checks": [],
            "evidence_policy": "Any"
          }
        ],
        "validation_refs": [],
        "is_abstract": false,
        "assignee": "codex-runtime-storage-boundary-redesign-2026-04-01",
        "base_revision": {
          "graph_version": 1144,
          "git_commit": null
        },
        "priority": null,
        "tags": [],
        "metadata": null
      },
      {
        "id": "coord-task:01knaddam3fvr96xdqdxn2xdsj",
        "plan_id": "plan:01knadcr3p15he31394q1bs5wv",
        "kind": "Edit",
        "title": "Implement remote shared-ref live sync and self-write suppression",
        "summary": null,
        "status": "Completed",
        "bindings": {
          "anchors": [],
          "concept_handles": [],
          "artifact_refs": [],
          "memory_refs": [],
          "outcome_refs": []
        },
        "acceptance": [
          {
            "label": "Runtime observes remote shared-ref head movement and imports it without self-churn.",
            "anchors": [],
            "required_checks": [],
            "evidence_policy": "Any"
          }
        ],
        "validation_refs": [],
        "is_abstract": false,
        "assignee": "codex-runtime-storage-boundary-redesign-2026-04-01",
        "base_revision": {
          "graph_version": 1155,
          "git_commit": null
        },
        "priority": null,
        "tags": [],
        "metadata": null
      },
      {
        "id": "coord-task:01knaddcdxvdyh8akrc10b9npw",
        "plan_id": "plan:01knadcr3p15he31394q1bs5wv",
        "kind": "Edit",
        "title": "Model target integration lifecycle and durable landing evidence",
        "summary": null,
        "status": "Completed",
        "bindings": {
          "anchors": [],
          "concept_handles": [],
          "artifact_refs": [],
          "memory_refs": [],
          "outcome_refs": []
        },
        "acceptance": [
          {
            "label": "Tasks can distinguish branch publication, shared coordination publication, and target integration with durable evidence.",
            "anchors": [],
            "required_checks": [],
            "evidence_policy": "Any"
          }
        ],
        "validation_refs": [],
        "is_abstract": false,
        "assignee": "codex-runtime-storage-boundary-redesign-2026-04-01",
        "base_revision": {
          "graph_version": 1183,
          "git_commit": null
        },
        "priority": null,
        "tags": [],
        "metadata": null
      },
      {
        "id": "coord-task:01knaddebyw5yp2vex9e8fgfm7",
        "plan_id": "plan:01knadcr3p15he31394q1bs5wv",
        "kind": "Edit",
        "title": "Add shared-ref retention, compaction, and operator diagnostics",
        "summary": null,
        "status": "Completed",
        "bindings": {
          "anchors": [],
          "concept_handles": [],
          "artifact_refs": [],
          "memory_refs": [],
          "outcome_refs": []
        },
        "acceptance": [
          {
            "label": "Shared coordination ref growth is bounded and operators can inspect compaction health.",
            "anchors": [],
            "required_checks": [],
            "evidence_policy": "Any"
          }
        ],
        "validation_refs": [],
        "is_abstract": false,
        "assignee": "codex-runtime-storage-boundary-redesign-2026-04-01",
        "base_revision": {
          "graph_version": 1183,
          "git_commit": null
        },
        "priority": null,
        "tags": [],
        "metadata": null
      },
      {
        "id": "coord-task:01knaddrkxtpmzwc9vsr1ykw1p",
        "plan_id": "plan:01knadcr3p15he31394q1bs5wv",
        "kind": "Edit",
        "title": "Validate shared-ref coordination follow-through end to end",
        "summary": null,
        "status": "Completed",
        "bindings": {
          "anchors": [],
          "concept_handles": [],
          "artifact_refs": [],
          "memory_refs": [],
          "outcome_refs": []
        },
        "acceptance": [
          {
            "label": "CAS retry, live sync, integration evidence, and compaction all validate under release-binary dogfooding.",
            "anchors": [],
            "required_checks": [],
            "evidence_policy": "Any"
          }
        ],
        "validation_refs": [],
        "is_abstract": false,
        "assignee": "codex-runtime-storage-boundary-redesign-2026-04-01",
        "base_revision": {
          "graph_version": 1183,
          "git_commit": null
        },
        "priority": null,
        "tags": [],
        "metadata": null
      }
    ],
    "edges": [
      {
        "id": "plan-edge:coord-task:01knaddrkxtpmzwc9vsr1ykw1p:depends-on:coord-task:01knadd8hh7hxr20jgcc46ywhe",
        "plan_id": "plan:01knadcr3p15he31394q1bs5wv",
        "from": "coord-task:01knaddrkxtpmzwc9vsr1ykw1p",
        "to": "coord-task:01knadd8hh7hxr20jgcc46ywhe",
        "kind": "DependsOn",
        "summary": null,
        "metadata": null
      },
      {
        "id": "plan-edge:coord-task:01knaddrkxtpmzwc9vsr1ykw1p:depends-on:coord-task:01knaddam3fvr96xdqdxn2xdsj",
        "plan_id": "plan:01knadcr3p15he31394q1bs5wv",
        "from": "coord-task:01knaddrkxtpmzwc9vsr1ykw1p",
        "to": "coord-task:01knaddam3fvr96xdqdxn2xdsj",
        "kind": "DependsOn",
        "summary": null,
        "metadata": null
      },
      {
        "id": "plan-edge:coord-task:01knaddrkxtpmzwc9vsr1ykw1p:depends-on:coord-task:01knaddcdxvdyh8akrc10b9npw",
        "plan_id": "plan:01knadcr3p15he31394q1bs5wv",
        "from": "coord-task:01knaddrkxtpmzwc9vsr1ykw1p",
        "to": "coord-task:01knaddcdxvdyh8akrc10b9npw",
        "kind": "DependsOn",
        "summary": null,
        "metadata": null
      },
      {
        "id": "plan-edge:coord-task:01knaddrkxtpmzwc9vsr1ykw1p:depends-on:coord-task:01knaddebyw5yp2vex9e8fgfm7",
        "plan_id": "plan:01knadcr3p15he31394q1bs5wv",
        "from": "coord-task:01knaddrkxtpmzwc9vsr1ykw1p",
        "to": "coord-task:01knaddebyw5yp2vex9e8fgfm7",
        "kind": "DependsOn",
        "summary": null,
        "metadata": null
      }
    ]
  },
  "executionOverlays": [
    {
      "node_id": "coord-task:01knadd8hh7hxr20jgcc46ywhe",
      "pending_handoff_to": null,
      "session": "session:01knacdqfzqz97qywe873qv2cm",
      "worktree_id": "worktree:8719dd7db144e96f",
      "branch_ref": "refs/heads/task/shared-coordination-refs",
      "effective_assignee": null,
      "awaiting_handoff_from": null,
      "git_execution": null
    },
    {
      "node_id": "coord-task:01knaddam3fvr96xdqdxn2xdsj",
      "pending_handoff_to": null,
      "session": "session:01knacdqfzqz97qywe873qv2cm",
      "worktree_id": "worktree:8719dd7db144e96f",
      "branch_ref": "refs/heads/task/shared-coordination-refs",
      "effective_assignee": null,
      "awaiting_handoff_from": null,
      "git_execution": null
    },
    {
      "node_id": "coord-task:01knaddcdxvdyh8akrc10b9npw",
      "pending_handoff_to": null,
      "session": "session:01knacdqfzqz97qywe873qv2cm",
      "worktree_id": "worktree:8719dd7db144e96f",
      "branch_ref": "refs/heads/task/shared-coordination-refs",
      "effective_assignee": null,
      "awaiting_handoff_from": null,
      "git_execution": null
    },
    {
      "node_id": "coord-task:01knaddebyw5yp2vex9e8fgfm7",
      "pending_handoff_to": null,
      "session": "session:01knacdqfzqz97qywe873qv2cm",
      "worktree_id": "worktree:8719dd7db144e96f",
      "branch_ref": "refs/heads/task/shared-coordination-refs",
      "effective_assignee": null,
      "awaiting_handoff_from": null,
      "git_execution": null
    },
    {
      "node_id": "coord-task:01knaddrkxtpmzwc9vsr1ykw1p",
      "pending_handoff_to": null,
      "session": "session:01knacdqfzqz97qywe873qv2cm",
      "worktree_id": "worktree:8719dd7db144e96f",
      "branch_ref": "refs/heads/task/shared-coordination-refs",
      "effective_assignee": null,
      "awaiting_handoff_from": null,
      "git_execution": null
    }
  ]
}
