{
  "kind": "coordination_task",
  "payload": {
    "acceptance": [
      {
        "anchors": [],
        "label": "Relevant daemon, bridge, launcher, runtime-state, and auth/authority code owners are identified with specific failure hypotheses."
      },
      {
        "anchors": [],
        "label": "The plan names where to instrument exit, restart, authority lookup, and bridge-auth invalidation paths."
      }
    ],
    "anchors": [],
    "assignee": null,
    "base_revision": {
      "git_commit": null,
      "graph_version": 14
    },
    "bindings": {
      "anchors": [],
      "artifact_refs": [],
      "concept_handles": [],
      "memory_refs": [],
      "outcome_refs": []
    },
    "branch_ref": null,
    "coordination_depends_on": [],
    "depends_on": [],
    "git_execution": {
      "integrationCommit": null,
      "integrationEvidence": null,
      "integrationMode": "external",
      "integrationStatus": "not_started",
      "lastPreflight": null,
      "lastPublish": null,
      "pendingTaskStatus": null,
      "publishCommit": null,
      "publishRef": null,
      "reviewArtifactRef": null,
      "sourceCommit": null,
      "sourceRef": null,
      "status": "not_started",
      "targetBranch": null,
      "targetCommitAtPublish": null,
      "targetRef": null
    },
    "id": "coord-task:01kn80ry7wvfr9w7gp0dw8s5s6",
    "integrated_depends_on": [],
    "is_abstract": false,
    "kind": "Investigate",
    "lease_expires_at": null,
    "lease_holder": null,
    "lease_refreshed_at": null,
    "lease_stale_at": null,
    "lease_started_at": null,
    "metadata": null,
    "pending_handoff_to": null,
    "plan": "plan:01kn80rqn6t0pgv1dt0zqay9j5",
    "priority": null,
    "published_task_status": null,
    "session": null,
    "status": "Completed",
    "summary": "Traced the daemon lifecycle, bridge reconnect, auth injection, and principal-registry paths; confirmed missing exit instrumentation, stale runtime-state pruning without observability, bridge retrying dead upstream URIs without restart escalation, and bridge auth reporting bound state without live authority validation.",
    "tags": [
      "auth",
      "daemon",
      "investigation"
    ],
    "title": "Trace daemon lifecycle, supervisor, and authority persistence paths in code",
    "validation_refs": [],
    "worktree_id": null
  },
  "schema_version": 1
}
